ttrpg_control_desk/__init__.py
ttrpg_control_desk/app.py
ttrpg_control_desk-0.1.1.dist-info/METADATA
ttrpg_control_desk-0.1.1.dist-info/WHEEL
ttrpg_control_desk-0.1.1.dist-info/entry_points.txt
ttrpg_control_desk-0.1.1.dist-info/licenses/LICENSE
ttrpg_control_desk-0.1.1.dist-info/RECORD
