Metadata-Version: 2.4
Name: ttrpg-control-desk
Version: 0.1.1
Summary: Dual-screen display tool for tabletop RPG game masters with fog of war, character portraits, and pointer
Project-URL: Homepage, https://gitlab.com/mesfoliesludiques/ttrpg-control-desk
Project-URL: Repository, https://gitlab.com/mesfoliesludiques/ttrpg-control-desk
Project-URL: Issues, https://gitlab.com/mesfoliesludiques/ttrpg-control-desk/-/issues
Author-email: Emmanuel Ruaud <em.ruaud@gmail.com>
License: MIT
License-File: LICENSE
Keywords: battlemap,display,dnd,fog-of-war,gamemaster,gm-tools,pathfinder,rpg,tabletop,ttrpg
Classifier: Development Status :: 4 - Beta
Classifier: Environment :: MacOS X :: Cocoa
Classifier: Environment :: Win32 (MS Windows)
Classifier: Environment :: X11 Applications :: Qt
Classifier: Intended Audience :: End Users/Desktop
Classifier: License :: OSI Approved :: MIT License
Classifier: Operating System :: OS Independent
Classifier: Programming Language :: Python :: 3
Classifier: Programming Language :: Python :: 3.9
Classifier: Programming Language :: Python :: 3.10
Classifier: Programming Language :: Python :: 3.11
Classifier: Programming Language :: Python :: 3.12
Classifier: Topic :: Games/Entertainment :: Role-Playing
Classifier: Topic :: Multimedia :: Graphics :: Viewers
Requires-Python: >=3.9
Requires-Dist: pyqt5>=5.15
